{"cameraMode":{"drawMode":0,"name":"Shaded","section":"Shading Mode"},"sceneLighting":false,"audioPlay":false,"sceneViewState":{"m_AlwaysRefresh":false,"showFog":true,"showSkybox":false,"showFlares":true,"showImageEffects":true,"showParticleSystems":true,"showVisualEffectGraphs":true,"m_FxEnabled":true},"in2DMode":false,"pivot":{"x":-5.959453105926514,"y":5.067187786102295,"z":-16.088911056518556},"rotation":{"x":-0.1625683307647705,"y":0.05433758348226547,"z":-0.008635354228317738,"w":-0.9852958917617798},"size":44.905452728271487,"orthographic":true}